realm/__init__.py
realm/cli/__init__.py
realm/cli/application.py
realm/cli/commands/__init__.py
realm/cli/commands/build.py
realm/cli/commands/init.py
realm/cli/commands/install.py
realm/cli/commands/ls.py
realm/cli/commands/run.py
realm/cli/commands/task.py
realm/cli/core/__init__.py
realm/cli/core/base_command.py
realm/cli/core/group.py
realm/cli/core/params.py
realm/cli/formatter.py
realm/cli/realm_click_types.py
realm/cli/realm_command.py
realm/entities/__init__.py
realm/entities/config.py
realm/entities/context.py
realm/entities/graph.py
realm/entities/project.py
realm/filters/__init__.py
realm/filters/ignore.py
realm/filters/match.py
realm/filters/scope.py
realm/filters/since.py
realm/log.py
realm/utils/__init__.py
realm/utils/child_process.py
realm/version.py
realm-0.4.1.dist-info/LICENSE
realm-0.4.1.dist-info/METADATA
realm-0.4.1.dist-info/WHEEL
realm-0.4.1.dist-info/entry_points.txt
realm-0.4.1.dist-info/RECORD
