Metadata-Version: 2.1
Name: realm
Version: 0.4.1
Summary: A tool for managing python poetry projects
Home-page: https://github.com/orlevii/realm
License: MIT
Keywords: monorepo,realm,poetry
Author: Or Levi
Author-email: orlevi128@gmail.com
Requires-Python: >=3.8.1,<4.0.0
Classifier: Development Status :: 5 - Production/Stable
Classifier: Intended Audience :: Developers
Classifier: License :: OSI Approved :: MIT License
Classifier: Operating System :: OS Independent
Classifier: Programming Language :: Python :: 3
Classifier: Programming Language :: Python :: 3.9
Classifier: Programming Language :: Python :: 3.10
Classifier: Programming Language :: Python :: 3.11
Classifier: Programming Language :: Python :: 3.12
Classifier: Programming Language :: Python :: 3 :: Only
Classifier: Topic :: Software Development :: Libraries
Provides-Extra: tasks
Requires-Dist: click (>=8.1.7,<9.0.0)
Requires-Dist: colorama (>=0.4.6,<0.5.0)
Requires-Dist: poethepoet (<1.0.0) ; extra == "tasks"
Requires-Dist: toml (>=0.10.2,<0.11.0)
Project-URL: Documentation, https://orlevii.github.io/realm/
Project-URL: Repository, https://github.com/orlevii/realm
